{
  "short_sleeve_top": "https://www.musinsa.com/category/001001",
  "long_sleeve_top": "https://www.musinsa.com/category/001",
  "sling": "https://www.musinsa.com/category/001011",
  "shorts": "https://www.musinsa.com/category/003009",
  "trousers": "https://www.musinsa.com/category/003",
  "skirt": "https://www.musinsa.com/category/100",
  "short_sleeve_outer": "https://www.musinsa.com/category/002",
  "long_sleeve_outer": "https://www.musinsa.com/category/002",
  "short_sleeve_dress": "https://www.musinsa.com/category/100",
  "long_sleeve_dress": "https://www.musinsa.com/category/100",
  "vest_dress": "https://www.musinsa.com/category/100",
  "sling_dress": "https://www.musinsa.com/category/100"
}